COPYING
MANIFEST.in
README
health_pediatrics_report.xml
health_pediatrics_view.xml
setup.py
./__init__.py
./health_pediatrics.py
./health_pediatrics_report.xml
./health_pediatrics_view.xml
./tryton.cfg
./doc/index.rst
./icons/baby_boy_sitting.svg
./locale/ar.po
./locale/de.po
./locale/el.po
./locale/es.po
./locale/fr.po
./locale/it_IT.po
./locale/ja_JP.po
./locale/lo.po
./locale/pt_BR.po
./locale/zh_CN.po
./report/newborn_card.odt
./security/access_rights.xml
./tests/__init__.py
./tests/test_health_pediatrics.py
./view/gnuhealth_neonatal_apgar.xml
./view/gnuhealth_neonatal_apgar_tree.xml
./view/gnuhealth_newborn.xml
./view/gnuhealth_newborn_tree.xml
./view/gnuhealth_pediatric_symptoms_checklist.xml
./view/gnuhealth_pediatric_symptoms_checklist_tree.xml
icons/README
icons/baby_boy_sitting.svg
locale/ar.po
locale/de.po
locale/el.po
locale/es.po
locale/fr.po
locale/it_IT.po
locale/ja_JP.po
locale/lo.po
locale/pt_BR.po
locale/zh_CN.po
report/newborn_card.odt
security/access_rights.xml
trytond_health_pediatrics.egg-info/PKG-INFO
trytond_health_pediatrics.egg-info/SOURCES.txt
trytond_health_pediatrics.egg-info/dependency_links.txt
trytond_health_pediatrics.egg-info/entry_points.txt
trytond_health_pediatrics.egg-info/not-zip-safe
trytond_health_pediatrics.egg-info/requires.txt
trytond_health_pediatrics.egg-info/top_level.txt
view/gnuhealth_neonatal_apgar.xml
view/gnuhealth_neonatal_apgar_tree.xml
view/gnuhealth_newborn.xml
view/gnuhealth_newborn_tree.xml
view/gnuhealth_pediatric_symptoms_checklist.xml
view/gnuhealth_pediatric_symptoms_checklist_tree.xml